academylib.py
academylibr-0.0.1.dist-info/METADATA
academylibr-0.0.1.dist-info/WHEEL
academylibr-0.0.1.dist-info/top_level.txt
academylibr-0.0.1.dist-info/RECORD
