Metadata-Version: 2.1
Name: academylibr
Version: 0.0.1
Summary: Academy 4 Summer Course
